[
  {
    "login":"elletjies",
    "contributions":538
  },
  {
    "login":"froggleston",
    "contributions":320
  },
  {
    "login":"fmichonneau",
    "contributions":235
  },
  {
    "login":"jsteyn",
    "contributions":166
  },
  {
    "login":"baileythegreen",
    "contributions":126
  },
  {
    "login":"zkamvar",
    "contributions":93
  },
  {
    "login":"gvwilson",
    "contributions":87
  },
  {
    "login":"ian-flores",
    "contributions":79
  },
  {
    "login":"nicoguaro",
    "contributions":50
  },
  {
    "login":"BatoolMM",
    "contributions":41
  },
  {
    "login":"TomKellyGenetics",
    "contributions":41
  },
  {
    "login":"YehorBoiar",
    "contributions":41
  },
  {
    "login":"VeronikaShevc",
    "contributions":40
  },
  {
    "login":"Herobread",
    "contributions":35
  },
  {
    "login":"marcosvital",
    "contributions":27
  },
  {
    "login":"sofiiamatios",
    "contributions":21
  },
  {
    "login":"feddelegrand7",
    "contributions":21
  },
  {
    "login":"MarieHouillon",
    "contributions":20
  },
  {
    "login":"NOngeso",
    "contributions":19
  },
  {
    "login":"MounaBelaid",
    "contributions":16
  },
  {
    "login":"VScharf7",
    "contributions":16
  },
  {
    "login":"tobyhodges",
    "contributions":15
  },
  {
    "login":"leticiadasilva",
    "contributions":15
  },
  {
    "login":"olexandr-konovalov",
    "contributions":13
  },
  {
    "login":"konrad",
    "contributions":13
  },
  {
    "login":"beatrizmilz",
    "contributions":13
  },
  {
    "login":"annajiat",
    "contributions":13
  },
  {
    "login":"jduckles",
    "contributions":12
  },
  {
    "login":"villares",
    "contributions":12
  },
  {
    "login":"NPalopoli",
    "contributions":11
  },
  {
    "login":"timtomch",
    "contributions":11
  },
  {
    "login":"callumrollo",
    "contributions":10
  },
  {
    "login":"demar01",
    "contributions":10
  },
  {
    "login":"dsmits",
    "contributions":9
  },
  {
    "login":"blacktack2",
    "contributions":9
  },
  {
    "login":"LilithElina",
    "contributions":8
  },
  {
    "login":"masamiy",
    "contributions":8
  },
  {
    "login":"ailisarre",
    "contributions":7
  },
  {
    "login":"kozo2",
    "contributions":6
  },
  {
    "login":"matiasmicheletto",
    "contributions":6
  },
  {
    "login":"josenino95",
    "contributions":5
  },
  {
    "login":"sfmig",
    "contributions":5
  },
  {
    "login":"yabellini",
    "contributions":5
  },
  {
    "login":"tyt3",
    "contributions":5
  },
  {
    "login":"rivaquiroga",
    "contributions":5
  },
  {
    "login":"paocorrales",
    "contributions":5
  },
  {
    "login":"ageorgou",
    "contributions":5
  },
  {
    "login":"RabeaMue",
    "contributions":4
  },
  {
    "login":"naoe-tatara",
    "contributions":4
  },
  {
    "login":"mariyaspatar",
    "contributions":4
  },
  {
    "login":"jesCodingHere",
    "contributions":4
  },
  {
    "login":"Taalmasoud",
    "contributions":4
  },
  {
    "login":"doerners",
    "contributions":4
  },
  {
    "login":"JorgeBornemann",
    "contributions":4
  },
  {
    "login":"IngaPa",
    "contributions":4
  },
  {
    "login":"imanalhasani",
    "contributions":4
  },
  {
    "login":"GorataB",
    "contributions":4
  },
  {
    "login":"Fehings",
    "contributions":4
  },
  {
    "login":"badryan",
    "contributions":4
  },
  {
    "login":"bkmgit",
    "contributions":4
  },
  {
    "login":"Alicia-Talavera",
    "contributions":4
  },
  {
    "login":"manuGil",
    "contributions":3
  },
  {
    "login":"lucaferranti",
    "contributions":3
  },
  {
    "login":"iramosp",
    "contributions":3
  },
  {
    "login":"criselsuarez",
    "contributions":3
  },
  {
    "login":"nucholab",
    "contributions":3
  },
  {
    "login":"MikeResearch",
    "contributions":3
  },
  {
    "login":"Armadilloa16",
    "contributions":3
  },
  {
    "login":"kkauder",
    "contributions":3
  },
  {
    "login":"kmbuki",
    "contributions":3
  },
  {
    "login":"Harry-Dolan",
    "contributions":3
  },
  {
    "login":"ftabaro",
    "contributions":3
  },
  {
    "login":"AngeliqueV",
    "contributions":3
  },
  {
    "login":"cmeessen",
    "contributions":3
  },
  {
    "login":"MysteryBlokHed",
    "contributions":2
  },
  {
    "login":"sstevens2",
    "contributions":2
  },
  {
    "login":"TueloNtlotlang",
    "contributions":2
  },
  {
    "login":"chaimae123-ai",
    "contributions":2
  },
  {
    "login":"dougdaniels",
    "contributions":2
  },
  {
    "login":"elsikorski",
    "contributions":2
  },
  {
    "login":"jameswarduwa",
    "contributions":2
  },
  {
    "login":"mdbjax",
    "contributions":2
  },
  {
    "login":"kashpit0507",
    "contributions":2
  },
  {
    "login":"talyacooper",
    "contributions":2
  },
  {
    "login":"za",
    "contributions":2
  },
  {
    "login":"ajneil-gh",
    "contributions":2
  },
  {
    "login":"corybrunson",
    "contributions":2
  },
  {
    "login":"imre",
    "contributions":2
  },
  {
    "login":"MRudey",
    "contributions":2
  },
  {
    "login":"abhicc",
    "contributions":2
  },
  {
    "login":"beamilz-ensino",
    "contributions":2
  },
  {
    "login":"ashwinvis",
    "contributions":2
  },
  {
    "login":"danielskatz",
    "contributions":2
  },
  {
    "login":"dannda",
    "contributions":2
  },
  {
    "login":"ealvaradomena",
    "contributions":2
  },
  {
    "login":"Eirinits",
    "contributions":2
  },
  {
    "login":"hpthatchfield",
    "contributions":2
  },
  {
    "login":"jamesrco",
    "contributions":2
  },
  {
    "login":"jananiharan",
    "contributions":2
  },
  {
    "login":"jcostacurta11",
    "contributions":2
  },
  {
    "login":"mugeha-laura",
    "contributions":2
  },
  {
    "login":"SamGuay",
    "contributions":2
  },
  {
    "login":"sandragodinhosilva",
    "contributions":2
  },
  {
    "login":"pri-hoh",
    "contributions":1
  },
  {
    "login":"radersma",
    "contributions":1
  },
  {
    "login":"rosemm",
    "contributions":1
  },
  {
    "login":"brownsarahm",
    "contributions":1
  },
  {
    "login":"ocesaulo",
    "contributions":1
  },
  {
    "login":"sayalaruano",
    "contributions":1
  },
  {
    "login":"ShrRa",
    "contributions":1
  },
  {
    "login":"souravsingh",
    "contributions":1
  },
  {
    "login":"svenvanderburg",
    "contributions":1
  },
  {
    "login":"tanjagaustad",
    "contributions":1
  },
  {
    "login":"PatriciaSA",
    "contributions":1
  },
  {
    "login":"paritoshk",
    "contributions":1
  },
  {
    "login":"pablotis",
    "contributions":1
  },
  {
    "login":"OscarSiba",
    "contributions":1
  },
  {
    "login":"nscherf",
    "contributions":1
  },
  {
    "login":"nanjalaruth",
    "contributions":1
  },
  {
    "login":"MilenaLa",
    "contributions":1
  },
  {
    "login":"mvzaanen",
    "contributions":1
  },
  {
    "login":"marionwalton",
    "contributions":1
  },
  {
    "login":"MarielenaS",
    "contributions":1
  },
  {
    "login":"mpaulacaldas",
    "contributions":1
  },
  {
    "login":"maneesha",
    "contributions":1
  },
  {
    "login":"lphegley",
    "contributions":1
  },
  {
    "login":"julievecchio",
    "contributions":1
  },
  {
    "login":"jnywong-test",
    "contributions":1
  },
  {
    "login":"heidikarlsen",
    "contributions":1
  },
  {
    "login":"gsavva",
    "contributions":1
  },
  {
    "login":"fraukero",
    "contributions":1
  },
  {
    "login":"evanmarzahn",
    "contributions":1
  },
  {
    "login":"eddUG",
    "contributions":1
  },
  {
    "login":"donatella-cea",
    "contributions":1
  },
  {
    "login":"domhnallc",
    "contributions":1
  },
  {
    "login":"cosmofelix",
    "contributions":1
  },
  {
    "login":"cmdalton",
    "contributions":1
  },
  {
    "login":"clem33",
    "contributions":1
  },
  {
    "login":"beacurious",
    "contributions":1
  },
  {
    "login":"agully1",
    "contributions":1
  },
  {
    "login":"joun58",
    "contributions":1
  },
  {
    "login":"winfrednyoroka",
    "contributions":1
  },
  {
    "login":"warrickball",
    "contributions":1
  },
  {
    "login":"eunicenjuguna",
    "contributions":1
  },
  {
    "login":"WafaaMoh",
    "contributions":1
  },
  {
    "login":"vguillemot",
    "contributions":1
  },
  {
    "login":"ewinge",
    "contributions":1
  },
  {
    "login":"d0rg0ld",
    "contributions":1
  },
  {
    "login":"diegoonna",
    "contributions":1
  },
  {
    "login":"D-Barradas",
    "contributions":1
  },
  {
    "login":"Deisiany",
    "contributions":1
  },
  {
    "login":"dannyba",
    "contributions":1
  },
  {
    "login":"CunliangGeng",
    "contributions":1
  },
  {
    "login":"clelange",
    "contributions":1
  },
  {
    "login":"Charlie-George",
    "contributions":1
  },
  {
    "login":"aguerodev",
    "contributions":1
  },
  {
    "login":"bawee",
    "contributions":1
  },
  {
    "login":"BioNomad",
    "contributions":1
  },
  {
    "login":"benbrecht",
    "contributions":1
  },
  {
    "login":"BFrit",
    "contributions":1
  },
  {
    "login":"amoneva",
    "contributions":1
  },
  {
    "login":"ahcvlot",
    "contributions":1
  },
  {
    "login":"sackmanna",
    "contributions":1
  },
  {
    "login":"SoyAndrea",
    "contributions":1
  },
  {
    "login":"Agrippina254",
    "contributions":1
  },
  {
    "login":"Dallak",
    "contributions":1
  },
  {
    "login":"b1nslashsh",
    "contributions":1
  },
  {
    "login":"MaggiK",
    "contributions":1
  },
  {
    "login":"Mabrouk12300",
    "contributions":1
  },
  {
    "login":"mmcsamcm",
    "contributions":1
  },
  {
    "login":"lmdabigail",
    "contributions":1
  },
  {
    "login":"lossanna",
    "contributions":1
  },
  {
    "login":"lmtnezg",
    "contributions":1
  },
  {
    "login":"edinkasia",
    "contributions":1
  },
  {
    "login":"jas1",
    "contributions":1
  },
  {
    "login":"JMorado",
    "contributions":1
  },
  {
    "login":"hernandezj1",
    "contributions":1
  },
  {
    "login":"johnbradley",
    "contributions":1
  },
  {
    "login":"Sibeko-J",
    "contributions":1
  },
  {
    "login":"likeajumprope",
    "contributions":1
  },
  {
    "login":"JClokey",
    "contributions":1
  },
  {
    "login":"ianvcaldas",
    "contributions":1
  },
  {
    "login":"gerhardvanh",
    "contributions":1
  },
  {
    "login":"GenevieveMilliken",
    "contributions":1
  },
  {
    "login":"fpozoc",
    "contributions":1
  },
  {
    "login":"FarzanaZAli",
    "contributions":1
  },
  {
    "login":"EveBigras",
    "contributions":1
  },
  {
    "login":"edfoster10",
    "contributions":1
  }
]